{
    "originalTeams": [
        {
            "name": "Anaheim Ducks",
            "imageLocation": "Anaheim.png",
            "abbreviation": "ANA"
        },
        {
            "name": "Arizona Coyotes",
            "imageLocation": "Arizona.png",
            "abbreviation": "ARI"
        },
        {
            "name": "Boston Bruins Coyotes",
            "imageLocation": "Boston.png",
            "abbreviation": "BOS"
        },
        {
            "name": "Buffalo Sabres",
            "imageLocation": "Buffalo.png",
            "abbreviation": "BUF"
        },
        {
            "name": "Calgary Flames",
            "imageLocation": "Calgary.png",
            "abbreviation": "CGY"
        },
        {
            "name": "Carolina Hurricanes",
            "imageLocation": "Carolina.png",
            "abbreviation": "CAR"
        },
        {
            "name": "Chicago Blackhawks",
            "imageLocation": "Chicago.png",
            "abbreviation": "CHI"
        },
        {
            "name": "Colorado Avalanche",
            "imageLocation": "Colorado.png",
            "abbreviation": "COL"
        },
        {
            "name": "Columbus Blue Jackets",
            "imageLocation": "Columbus.png",
            "abbreviation": "CBJ"
        },
        {
            "name": "Dallas Stars",
            "imageLocation": "Dallas.png",
            "abbreviation": "DAL"
        },
        {
            "name": "Detroit Red Wings",
            "imageLocation": "Detroit.png",
            "abbreviation": "DET"
        },
        {
            "name": "Edmonton Oilers",
            "imageLocation": "Edmonton.png",
            "abbreviation": "EDM"
        },
        {
            "name": "Florida Panthers",
            "imageLocation": "Florida.png",
            "abbreviation": "FLA"
        },
        {
            "name": "Los Angeles Kings",
            "imageLocation": "Los Angeles.png",
            "abbreviation": "LAK"
        },
        {
            "name": "Minnesota Wild",
            "imageLocation": "Minnesota.png",
            "abbreviation": "MIN"
        },
        {
            "name": "Montreal Canadiens",
            "imageLocation": "Montreal.png",
            "abbreviation": "MTL"
        },
        {
            "name": "Nashville Predators",
            "imageLocation": "Nashville.png",
            "abbreviation": "NSH"
        },
        {
            "name": "New Jersey Devils",
            "imageLocation": "New Jersey.png",
            "abbreviation": "NJD"
        },
        {
            "name": "New York Islanders",
            "imageLocation": "New York 1.png",
            "abbreviation": "NYI"
        },
        {
            "name": "New York Rangers",
            "imageLocation": "New York 2.png",
            "abbreviation": "NYR"
        },
        {
            "name": "Ottawa Senators",
            "imageLocation": "Ottawa.png",
            "abbreviation": "OTT"
        },
        {
            "name": "Philadelphia Flyers",
            "imageLocation": "Philadelphia.png",
            "abbreviation": "PHI"
        },
        {
            "name": "Pittsburgh Penguins",
            "imageLocation": "Pittsburgh.png",
            "abbreviation": "PIT"
        },
        {
            "name": "San Jose Sharks",
            "imageLocation": "San Jose.png",
            "abbreviation": "SJS"
        },
        {
            "name": "St. Louis Blues",
            "imageLocation": "St. Louis.png",
            "abbreviation": "STL"
        },
        {
            "name": "Tampa Bay Lightning",
            "imageLocation": "Tampa Bay.png",
            "abbreviation": "TBL"
        },
        {
            "name": "Toronto Maple Leafs",
            "imageLocation": "Toronto.png",
            "abbreviation": "TOR"
        },
        {
            "name": "Vancouver Canucks",
            "imageLocation": "Vancouver.png",
            "abbreviation": "VAN"
        },
        {
            "name": "Washington Capitals",
            "imageLocation": "Washington.png",
            "abbreviation": "WAS"
        },
        {
            "name": "Winnipeg Jets",
            "imageLocation": "Winnipeg.png",
            "abbreviation": "WPJ"
        }
    ],
    "expansionTeam": [
        {
            "name": "Seattle Kraken",
            "imageLocation": "Anaheim.png",
            "abbreviation": "SEA"
        }
    ]
}